genai_colosseum_premium/__init__.py
genai_colosseum_premium/cli.py
genai_colosseum_premium/installer.py
genai_colosseum_premium/license_client.py
genai_colosseum_premium/templates/chatbot/chatbot/QUICK_START.md
genai_colosseum_premium/templates/chatbot/chatbot/README.md
genai_colosseum_premium/templates/chatbot/chatbot/app.py
genai_colosseum_premium/templates/chatbot/chatbot/create_venv.sh
genai_colosseum_premium/templates/chatbot/chatbot/env_template.txt
genai_colosseum_premium/templates/chatbot/chatbot/requirements.txt
genai_colosseum_premium/templates/chatbot/chatbot/setup.py
genai_colosseum_premium/templates/code_gen/code_gen/QUICK_START.md
genai_colosseum_premium/templates/code_gen/code_gen/README.md
genai_colosseum_premium/templates/code_gen/code_gen/component_descriptions.txt
genai_colosseum_premium/templates/code_gen/code_gen/create_venv.sh
genai_colosseum_premium/templates/code_gen/code_gen/env_template.txt
genai_colosseum_premium/templates/code_gen/code_gen/main.py
genai_colosseum_premium/templates/code_gen/code_gen/requirements.txt
genai_colosseum_premium/templates/code_gen/code_gen/setup.py
genai_colosseum_premium/templates/rag_pipeline/rag_pipeline/QUICK_START.md
genai_colosseum_premium/templates/rag_pipeline/rag_pipeline/README.md
genai_colosseum_premium/templates/rag_pipeline/rag_pipeline/create_venv.sh
genai_colosseum_premium/templates/rag_pipeline/rag_pipeline/env_template.txt
genai_colosseum_premium/templates/rag_pipeline/rag_pipeline/rag_implementation.py
genai_colosseum_premium/templates/rag_pipeline/rag_pipeline/requirements.txt
genai_colosseum_premium/templates/rag_pipeline/rag_pipeline/setup.py
genai_colosseum_premium/templates/rag_pipeline/rag_pipeline/speech.txt
genai_colosseum_premium/templates/rag_pipeline/rag_pipeline/test_embeddings.py
genai_colosseum_premium/templates/trial_transcription/trial_transcription/QUICK_START.md
genai_colosseum_premium/templates/trial_transcription/trial_transcription/README.md
genai_colosseum_premium-0.2.4.dist-info/METADATA
genai_colosseum_premium-0.2.4.dist-info/WHEEL
genai_colosseum_premium-0.2.4.dist-info/entry_points.txt
genai_colosseum_premium-0.2.4.dist-info/top_level.txt
genai_colosseum_premium-0.2.4.dist-info/RECORD
