Metadata-Version: 2.4
Name: genai_colosseum_premium
Version: 0.2.4
Requires-Dist: click
Requires-Dist: requests
Dynamic: requires-dist
